[
    {
        "FilterGroup": 0,
        "FilterOperator": "=",
        "FilterValue": "CaseId",
        "GlobalKey": "fb00b463-bce8-4145-a235-830bb234e083",
        "InputFieldName": "ParentId",
        "InputObjectName": "CaseComment",
        "InputObjectQuerySequence": 1,
        "IsDisabled": false,
        "IsRequiredForUpsert": false,
        "IsUpsertKey": false,
        "Name": "sampleGetCaseComments",
        "OmniDataTransformationId": {
            "Name": "sampleGetCaseComments",
            "VlocityDataPackType": "VlocityMatchingKeyObject",
            "VlocityMatchingRecordSourceKey": "OmniDataTransform/sampleGetCaseComments",
            "VlocityRecordSObjectType": "OmniDataTransform"
        },
        "OutputCreationSequence": 0,
        "OutputFieldName": "CaseComment",
        "OutputObjectName": "json",
        "VlocityDataPackType": "SObject",
        "VlocityRecordSObjectType": "OmniDataTransformItem"
    },
    {
        "GlobalKey": "9297aa4a-57e6-45e1-9cec-58afe7b6a8d1",
        "IsDisabled": false,
        "IsRequiredForUpsert": false,
        "IsUpsertKey": false,
        "Name": "sampleGetCaseComments",
        "OmniDataTransformationId": {
            "Name": "sampleGetCaseComments",
            "VlocityDataPackType": "VlocityMatchingKeyObject",
            "VlocityMatchingRecordSourceKey": "OmniDataTransform/sampleGetCaseComments",
            "VlocityRecordSObjectType": "OmniDataTransform"
        },
        "OutputCreationSequence": 1,
        "OutputFieldFormat": "List<Map>",
        "OutputFieldName": "CaseComments",
        "OutputObjectName": "json",
        "VlocityDataPackType": "SObject",
        "VlocityRecordSObjectType": "OmniDataTransformItem"
    },
    {
        "GlobalKey": "14a1e6ba-446d-4ee8-bc1e-c5a74740ee01",
        "InputFieldName": "CaseComment:CommentBody",
        "IsDisabled": false,
        "IsRequiredForUpsert": false,
        "IsUpsertKey": false,
        "Name": "sampleGetCaseComments",
        "OmniDataTransformationId": {
            "Name": "sampleGetCaseComments",
            "VlocityDataPackType": "VlocityMatchingKeyObject",
            "VlocityMatchingRecordSourceKey": "OmniDataTransform/sampleGetCaseComments",
            "VlocityRecordSObjectType": "OmniDataTransform"
        },
        "OutputCreationSequence": 1,
        "OutputFieldName": "CaseComments:Comment",
        "OutputObjectName": "json",
        "VlocityDataPackType": "SObject",
        "VlocityRecordSObjectType": "OmniDataTransformItem"
    },
    {
        "GlobalKey": "a9784a92-29b3-40f3-9223-05d72a01de63",
        "InputFieldName": "CaseComment:CreatedDate",
        "IsDisabled": false,
        "IsRequiredForUpsert": false,
        "IsUpsertKey": false,
        "Name": "sampleGetCaseComments",
        "OmniDataTransformationId": {
            "Name": "sampleGetCaseComments",
            "VlocityDataPackType": "VlocityMatchingKeyObject",
            "VlocityMatchingRecordSourceKey": "OmniDataTransform/sampleGetCaseComments",
            "VlocityRecordSObjectType": "OmniDataTransform"
        },
        "OutputCreationSequence": 1,
        "OutputFieldFormat": "Date(MM/dd/yyyy)",
        "OutputFieldName": "CaseComments:CreatedDate",
        "OutputObjectName": "json",
        "VlocityDataPackType": "SObject",
        "VlocityRecordSObjectType": "OmniDataTransformItem"
    },
    {
        "GlobalKey": "5bc7ecf0-9329-4a57-a2ae-d29362010a47",
        "InputFieldName": "CaseComment:IsPublished",
        "IsDisabled": false,
        "IsRequiredForUpsert": false,
        "IsUpsertKey": false,
        "Name": "sampleGetCaseComments",
        "OmniDataTransformationId": {
            "Name": "sampleGetCaseComments",
            "VlocityDataPackType": "VlocityMatchingKeyObject",
            "VlocityMatchingRecordSourceKey": "OmniDataTransform/sampleGetCaseComments",
            "VlocityRecordSObjectType": "OmniDataTransform"
        },
        "OutputCreationSequence": 1,
        "OutputFieldName": "CaseComments:IsPublished",
        "OutputObjectName": "json",
        "VlocityDataPackType": "SObject",
        "VlocityRecordSObjectType": "OmniDataTransformItem"
    }
]