{
    "IsActive": true,
    "IsOmniScriptEmbeddable": false,
    "Name": "DRChangeContactTA",
    "OmniProcessId": {
        "Name": "Sample Update Account Primary Contact 4-11 Weather",
        "VlocityDataPackType": "VlocityMatchingKeyObject",
        "VlocityMatchingRecordSourceKey": "OmniProcess/sample/updateAccountPrimaryContact/English",
        "VlocityRecordSObjectType": "OmniProcess"
    },
    "ParentElementId": {
        "Name": "TAChangeContact",
        "OmniProcessId": {
            "Name": "Sample Update Account Primary Contact 4-11 Weather",
            "VlocityDataPackType": "VlocityMatchingKeyObject",
            "VlocityMatchingRecordSourceKey": "OmniProcess/sample/updateAccountPrimaryContact/English",
            "VlocityRecordSObjectType": "OmniProcess"
        },
        "VlocityDataPackType": "VlocityMatchingKeyObject",
        "VlocityMatchingRecordSourceKey": "OmniProcessElement/OmniProcess/sample/updateAccountPrimaryContact/English/TAChangeContact",
        "VlocityRecordSObjectType": "OmniProcessElement"
    },
    "ParentElementName": "TAChangeContact",
    "ParentElementType": "Type Ahead Block",
    "PropertySetConfig": {
        "HTMLTemplateId": "",
        "bundle": "sampleChangePriContactTA",
        "controlWidth": 12,
        "dataRaptor Input Parameters": [
            {
                "element": "ContextId",
                "inputParam": "AccountId"
            },
            {
                "element": "TAChangeContact",
                "inputParam": "LookupKey"
            }
        ],
        "disOnTplt": false,
        "enableDefaultAbort": false,
        "errorMessage": {
            "custom": [
            ],
            "default": null
        },
        "failureAbortLabel": "Abort",
        "failureAbortMessage": "Are you sure?",
        "failureGoBackLabel": "Go Back",
        "failureNextLabel": "Continue",
        "inProgressMessage": "In Progress",
        "label": "DataRaptorExtractAction2",
        "message": {
        },
        "postMessage": "Done",
        "redirectNextLabel": "Next",
        "redirectNextWidth": 3,
        "redirectPageName": "",
        "redirectPreviousLabel": "Previous",
        "redirectPreviousWidth": 3,
        "redirectTemplateUrl": "vlcAcknowledge.html",
        "remoteTimeout": 30000,
        "responseJSONNode": "",
        "responseJSONPath": "",
        "show": null,
        "showPersistentComponent": [
            false,
            false
        ],
        "ssm": false,
        "validationRequired": "Step",
        "wpm": false
    },
    "Type": "DataRaptor Extract Action",
    "VlocityDataPackType": "SObject",
    "VlocityRecordSObjectType": "OmniProcessElement",
    "VlocityRecordSourceKey": "OmniProcessElement/OmniProcess/sample/updateAccountPrimaryContact/English/DRChangeContactTA"
}